<?xml version='1.0' encoding='UTF-8'?>  
<!DOCTYPE hibernate-mapping PUBLIC  
 "-//Hibernate/Hibernate Mapping DTD 5.3//EN"  
 "http://hibernate.sourceforge.net/hibernate-mapping-5.3.dtd">  
 
 <hibernate-mapping>
 
 <class name="mypack.entity.NoteEntity" table="NoteMaker">
 
     <id name="user_id">
     
     <generator class="increment"></generator>
     
     </id>
     
    
     
     <property name="title"></property>
     
      <property name="content"></property>
      
       <property name="addedDate"></property>
 
 </class>
 
 </hibernate-mapping>